datetoolz/__init__.py
datetoolz/core.py
datetoolz/__pycache__/__init__.cpython-313.pyc
datetoolz/__pycache__/core.cpython-313.pyc
datetoolz-0.1.0.dist-info/licenses/LICENSE
datetoolz-0.1.0.dist-info/METADATA
datetoolz-0.1.0.dist-info/WHEEL
datetoolz-0.1.0.dist-info/top_level.txt
datetoolz-0.1.0.dist-info/RECORD
