Metadata-Version: 2.4
Name: datetoolz
Version: 0.1.0
Summary: Tiny date helper library - get today, yesterday, tomorrow, weekday, etc.
Author-email: Jayanth Sanku <jaythedataguy@gmail.com>
License: MIT
Keywords: date,datetime,helpers
Classifier: Programming Language :: Python :: 3
Classifier: License :: OSI Approved :: MIT License
Classifier: Operating System :: OS Independent
Requires-Python: >=3.8
License-File: LICENSE
Dynamic: license-file
